[
    {
        "_id" : "55b57339ac6c1d02a6222727",
        "description" : "Admin",
        "name" : "Admin",
        "privileges" : { "metadata_uniquename" : 1,
        "fetch" : 1,
        "correct" : 1,
        "kill" : 1,
        "groups" : 1,
        "users" : 1,
        "ingest_providers" : 1,
        "unlock" : 1,
        "publish_filters" : 1,
        "tasks" : 1,
        "hold" : 1,
        "roles" : 1,
        "publish" : 1,
        "routing_rules" : 1,
        "spike" : 1,
        "content_templates" : 1,
        "ingest" : 1,
        "highlights" : 1,
        "planning" : 1,
        "publish_queue" : 1,
        "duplicate" : 1,
        "textarchive" : 1,
        "subscribers" : 1,
        "move" : 1,
        "saved_searches" : 1,
        "archive" : 1,
        "desks" : 1,
        "rule_sets" : 1,
        "restore" : 1,
        "dictionaries" : 1,
        "mark_for_highlights" : 1,
        "unspike" : 1,
        "legal_archive" : 1 }
     },
     {
        "_id" : "55b5734fac6c1d02a886c8ee",
        "description" : "Editor",
        "name" : "Editor",
        "is_default" : true
     }
]
